lute_khmer_parser/__init__.py
lute_khmer_parser/parser.py
lute3_khmer-0.0.3.dist-info/entry_points.txt
lute3_khmer-0.0.3.dist-info/WHEEL
lute3_khmer-0.0.3.dist-info/METADATA
lute3_khmer-0.0.3.dist-info/RECORD
