Metadata-Version: 2.1
Name: lute3-khmer
Version: 0.0.3
Summary: Learning Using Texts - Khmer Parser
Author: Justin Dom
Requires-Python: >=3.8
Requires-Dist: lute3>=3.4.2
Requires-Dist: khmer-nltk==1.6
